gemd/__init__.py
gemd/__version__.py
gemd/builders/__init__.py
gemd/builders/impl.py
gemd/demo/__init__.py
gemd/demo/cake.py
gemd/demo/material_run_example.py
gemd/demo/measurement_example.py
gemd/demo/strehlow_and_cook.pif
gemd/demo/strehlow_and_cook.py
gemd/demo/strehlow_and_cook_small.pif
gemd/demo/table_example.py
gemd/demo/toothpick.jpg
gemd/entity/__init__.py
gemd/entity/base_entity.py
gemd/entity/bounds_validation.py
gemd/entity/case_insensitive_dict.py
gemd/entity/dict_serializable.py
gemd/entity/file_link.py
gemd/entity/has_dependencies.py
gemd/entity/link_by_uid.py
gemd/entity/setters.py
gemd/entity/util.py
gemd/entity/valid_list.py
gemd/entity/attribute/__init__.py
gemd/entity/attribute/base_attribute.py
gemd/entity/attribute/condition.py
gemd/entity/attribute/parameter.py
gemd/entity/attribute/property.py
gemd/entity/attribute/property_and_conditions.py
gemd/entity/bounds/__init__.py
gemd/entity/bounds/base_bounds.py
gemd/entity/bounds/categorical_bounds.py
gemd/entity/bounds/composition_bounds.py
gemd/entity/bounds/integer_bounds.py
gemd/entity/bounds/molecular_structure_bounds.py
gemd/entity/bounds/real_bounds.py
gemd/entity/object/__init__.py
gemd/entity/object/base_object.py
gemd/entity/object/has_conditions.py
gemd/entity/object/has_material.py
gemd/entity/object/has_parameters.py
gemd/entity/object/has_process.py
gemd/entity/object/has_properties.py
gemd/entity/object/has_quantities.py
gemd/entity/object/has_source.py
gemd/entity/object/has_spec.py
gemd/entity/object/has_template.py
gemd/entity/object/has_template_check_generator.py
gemd/entity/object/ingredient_run.py
gemd/entity/object/ingredient_spec.py
gemd/entity/object/material_run.py
gemd/entity/object/material_spec.py
gemd/entity/object/measurement_run.py
gemd/entity/object/measurement_spec.py
gemd/entity/object/process_run.py
gemd/entity/object/process_spec.py
gemd/entity/source/__init__.py
gemd/entity/source/performed_source.py
gemd/entity/template/__init__.py
gemd-2.2.0.dist-info/LICENSE
gemd-2.2.0.dist-info/METADATA
gemd-2.2.0.dist-info/WHEEL
gemd-2.2.0.dist-info/top_level.txt
gemd-2.2.0.dist-info/RECORD
